forgehg/__init__.py
forgehg/controllers.py
forgehg/hg_main.py
forgehg/version.py
forgehg/model/__init__.py
forgehg/model/hg.py
forgehg/nf/hg/images/hg.png
forgehg/templates/__init__.py
forgehg/templates/hg/index.html
forgehg-0.5.4.dist-info/licenses/LICENSE
forgehg-0.5.4.dist-info/METADATA
forgehg-0.5.4.dist-info/WHEEL
forgehg-0.5.4.dist-info/entry_points.txt
forgehg-0.5.4.dist-info/top_level.txt
forgehg-0.5.4.dist-info/zip-safe
forgehg-0.5.4.dist-info/RECORD
